hasher/__init__.py
hasher/hasher.py
hasher_AlexHenderson-1.1.1.dist-info/LICENSE
hasher_AlexHenderson-1.1.1.dist-info/METADATA
hasher_AlexHenderson-1.1.1.dist-info/WHEEL
hasher_AlexHenderson-1.1.1.dist-info/top_level.txt
hasher_AlexHenderson-1.1.1.dist-info/RECORD
