Metadata-Version: 2.1
Name: hasher-AlexHenderson
Version: 1.1.1
Summary: Python package to generate a stable hash value for either a single file, or a folder containing many files and sub-folders.
Home-page: https://github.com/AlexHenderson/hasher
Author: Alex Henderson
Author-email: alex.henderson@manchester.ac.uk
License: UNKNOWN
Project-URL: Bug Tracker, https://github.com/AlexHenderson/hasher/issues
Platform: UNKNOWN
Classifier: Programming Language :: Python :: 3
Classifier: Programming Language :: Python :: 3.7
Classifier: License :: OSI Approved :: MIT License
Classifier: Operating System :: OS Independent
Classifier: Development Status :: 5 - Production/Stable
Classifier: Intended Audience :: Developers
Requires-Python: >=3.7
License-File: LICENSE
Requires-Dist: pytest (>=7.0.1)
